Workbook

Sheet Balance Sheet
A1: Netflix Balance Sheet
A3: in thousands | B3: 2018 | C3: 2019 | D3: 2020
A4: Assets
A5: Current assets
A6: Cash and cash equivalents | B6: 3794483 | C6: 5018437 | D6: 8205550 | F6: Cashflow
A7: Other current asssets | B7: 5899652 | C7: 1160067 | D7: 1556030
A8: Total current assets | B8: =SUM(B6:B7) -> 9694135 | C8: =SUM(C6:C7) -> 6178504 | D8: =SUM(D6:D7) -> 9761580
A9: content assets, net | B9: 14951141 | C9: 24504567 | D9: 25383950 | F9: Schedules
A10: property and equipment, net | B10: 418281 | C10: 565221 | D10: 960183 | F10: Schedules
A11: Other non-current assets | B11: 910843 | C11: 2727420 | D11: 3174646
A12: Total assets | B12: =SUM(B8:B11) -> 25974400 | C12: =SUM(C8:C11) -> 33975712 | D12: =SUM(D8:D11) -> 39280359
A14: Liabilities and Stockholders equity
A15: Current liabilities
A16: Current content liabilities | B16: 0 | C16: 4413561 | D16: 4429536
A17: Accounts payable | B17: 562985 | C17: 674347 | D17: 656183 | F17: Other items
A18: Accured expenses and other liabilities | B18: 481874 | C18: 843043 | D18: 1102196
A19: Deffered revenue | B19: 760899 | C19: 924745 | D19: 1117992
A20: Short term debt | D20: 499878
A21: Total current liabilities | B21: =SUM(B16:B20) -> 1805758 | C21: =SUM(C16:C20) -> 6855696 | D21: =SUM(D16:D20) -> 7805785
A22: Non-current content liabilities | B22: 3759026 | C22: 3334323 | D22: 2618084
A23: Long-term debt | B23: 10360058 | C23: 14759260 | D23: 15809095
A24: Other non-current liabilities | B24: 129231 | C24: 1444276 | D24: 1982155
A25: Total liabilities | B25: =SUM(B21:B24) -> 16054073 | C25: =SUM(C21:C24) -> 26393555 | D25: =SUM(D21:D24) -> 28215119
A26: Stockholders equity
A27: Common Stock | B27: 2315988 | C27: 2793929 | D27: 3447698
A28: Treasury stock
A29: Accumulated other comprehensive income (loss) | B29: -19582 | C29: -23521 | D29: 44398
A30: Retained earnings | B30: 2942359 | C30: 4811749 | D30: 7573144
A31: Total stockholders equity | B31: =SUM(B27:B30) -> 5238765 | C31: =SUM(C27:C30) -> 7582157 | D31: =SUM(D27:D30) -> 11065240
A32: Total liabilities and stockholders equity | B32: =SUM(B25+B31) -> 21292838 | C32: =SUM(C25+C31) -> 33975712 | D32: =SUM(D25+D31) -> 39280359

Sheet P&L
A1: P&L Statement
A3: in thousands | B3: 2018 | C3: 2019 | D3: 2020
A4: Revenues | B4: 15794341 | C4: 20156447 | D4: 24996056
A5: Cost of revenues | B5: 9967538 | C5: 12440213 | D5: 15276319
A6: Marketing | B6: 2369469 | C6: 2652462 | D6: 2228362
A7: Technology and development | B7: 1221814 | C7: 1545149 | D7: 1829600
A8: General and administrative | B8: 630294 | C8: 914369 | D8: 1076486
A9: Operating income | B9: 1605226 | C9: 2604254 | D9: 4585289
A10: Other income(expense)
A11: Interest | B11: -420493 | C11: -626023 | D11: -767499
A12: Interest and other income( expense) | B12: 41725 | C12: 84000 | D12: -618441
A13: Income before income tax | B13: 1226458 | C13: 2062231 | D13: 3199349
A14: Provision for income taxes | B14: -15216 | C14: -195315 | D14: -437954
A15: Net income | B15: 1211242 | C15: 1866916 | D15: 2761395

Sheet Revenue Modelling
A1: Revenue Sources
A2: in thousands | B2: 2018 | C2: 2019 | D2: 2020 | E2: 2021 Forcasted | F2: 2022 Forcasted | G2: 2023 Forcasted | H2: 2024 Forcasted
A3: Streaming revenues | B3: =B4+B10+B17+B24+B31 -> 15794341 | C3: =C4+C10+C17+C24+C31 -> 20156447 | D3: =D4+D10+D17+D24+D31 -> 24995956 | E3: =E4+E10+E17+E24+E31 -> 28644186 | F3: =F4+F10+F17+F24+F31 -> 33612322 | G3: =G4+G10+G17+G24+G31 -> 38290668 | H3: =H4+H10+H17+H24+H31 -> 42970088
A4: DVD Revenues | B4: 365589 | C4: 297217 | D4: 239281 | E4: =D4*(1+E5) -> 193584.67 | F4: =E4*(1+F5) -> 156615.12 | G4: =F4*(1+G5) -> 126705.78 | H4: =G4*(1+H5) -> 102508.33
A5: Growth % | C5: =C4/B4-1 -> -0.18701876 | D5: =D4/C4-1 -> -0.19492828 | E5: =AVERAGE($C$5:$D$5) -> -0.19097352 | F5: =AVERAGE($C$5:$D$5) -> -0.19097352 | G5: =AVERAGE($C$5:$D$5) -> -0.19097352 | H5: =AVERAGE($C$5:$D$5) -> -0.19097352
A6: Total Revenues | B6: =B3+B4 -> 16159930 | C6: =C3+C4 -> 20453664 | D6: =D3+D4 -> 25235237 | E6: =E3+E4 -> 28837771 | F6: =F3+F4 -> 33768937 | G6: =G3+G4 -> 38417374 | H6: =H3+H4 -> 43072597
A9: Unites States and Canada | I9: Average Monthly Revenues
A10: Revenues | B10: 8281532 | C10: 10051208 | D10: 11455396 | E10: =E12*E11 -> 11434119 | F10: =F12*F11 -> 12303514 | G10: =G12*G11 -> 13242115 | H10: =H12*H11 -> 14250649 | I10: 2018 | J10: 2019 | K10: 2020
A11: Average yearly revenue per membership | B11: =I11*12 -> 133.92 | C11: =J11*12 -> 150.84 | D11: =K11*12 -> 159.84 | E11: =AVERAGE($B$11:$D$11) -> 148.2 | F11: =AVERAGE($B$11:$D$11) -> 148.2 | G11: =AVERAGE($B$11:$D$11) -> 148.2 | H11: =AVERAGE($B$11:$D$11) -> 148.2 | I11: 11.16 | J11: 12.57 | K11: 13.32
A12: Average paid membership | B12: =B10/B11 -> 61839.397 | C12: =C10/C11 -> 66634.898 | D12: =D10/D11 -> 71667.893 | E12: =D12*(1+E13) -> 77153.303 | F12: =E12*(1+F13) -> 83019.662 | G12: =F12*(1+G13) -> 89353 | H12: =G12*(1+H13) -> 96158.228
A13: Growth % | C13: =C12/B12-1 -> 0.077547672 | D13: =D12/C12-1 -> 0.075530918 | E13: =AVERAGE(C13:D13) -> 0.076539295 | F13: =AVERAGE(D13:E13) -> 0.076035106 | G13: =AVERAGE(E13:F13) -> 0.076287201 | H13: =AVERAGE(F13:G13) -> 0.076161153
A16: Europe, Middle East and Africa | I16: Average Monthly Revenues
A17: Revenues | B17: 3963707 | C17: 5543067 | D17: 7772252 | E17: =E19*E18 -> 9981422.6 | F17: =F19*F18 -> 12088960 | G17: =G19*G18 -> 13432600 | H17: =H19*H18 -> 14656928 | I17: 2018 | J17: 2019 | K17: 2020
A18: Average yearly revenue per membership | B18: =I18*12 -> 125.4 | C18: =J18*12 -> 123.96 | D18: =K18*12 -> 128.64 | E18: =AVERAGE($B$18:$D$18) -> 126 | F18: =AVERAGE($B$18:$D$18) -> 126 | G18: =AVERAGE($B$18:$D$18) -> 126 | H18: =AVERAGE($B$18:$D$18) -> 126 | I18: 10.45 | J18: 10.33 | K18: 10.72
A19: Average paid membership | B19: =B17/B18 -> 31608.509 | C19: =C17/C18 -> 44716.578 | D19: =D17/D18 -> 60418.626 | E19: =D19*(1+E20) -> 79217.64 | F19: =E19*(1+F20) -> 95944.128 | G19: =F19*(1+G20) -> 106607.93 | H19: =G19*(1+H20) -> 116324.82
A20: Growth % | C20: =C19/B19-1 -> 0.41470065 | D20: =D19/C19-1 -> 0.351146 | E20: =D20-4% -> 0.311146 | F20: =E20-10% -> 0.211146 | G20: =F20-10% -> 0.111146 | H20: =G20-2% -> 0.091146005
A23: Latin America | J23: Average Monthly Revenues
A24: Revenues | B24: 2237697 | C24: 2795434 | D24: 3156727 | E24: =E26*E25 -> 3842573.8 | F24: =F26*F25 -> 4429558.5 | G24: =G26*G25 -> 4995470.9 | H24: =H26*H25 -> 5508796.6 | I24: 2018 | J24: 2019 | K24: 2020
A25: Average yearly revenue per membership | B25: =I25*12 -> 111.96 | C25: =J25*12 -> 110.88 | D25: =K25*12 -> 109.44 | E25: =AVERAGE(($B$25:$D$25)) -> 110.76 | F25: =AVERAGE(($B$25:$D$25)) -> 110.76 | G25: =AVERAGE(($B$25:$D$25)) -> 110.76 | H25: =AVERAGE(($B$25:$D$25)) -> 110.76 | I25: 9.33 | J25: 9.24 | K25: 9.12
A26: Average paid membership | B26: =B24/B25 -> 19986.576 | C26: =C24/C25 -> 25211.346 | D26: =D24/D25 -> 28844.362 | E26: =D26*(1+E27) -> 34692.793 | F26: =E26*(1+F27) -> 39992.402 | G26: =F26*(1+G27) -> 45101.76 | H26: =G26*(1+H27) -> 49736.336
A27: Growth % | C27: =C26/B26-1 -> 0.26141397 | D27: =D26/C26-1 -> 0.14410245 | E27: =AVERAGE(C27:D27) -> 0.20275821 | F27: =E27-5% -> 0.15275821 | G27: =F27-2.5% -> 0.12775821 | H27: =G27-2.5% -> 0.10275821
A30: Asia-Pacific | J30: Average Monthly Revenues
A31: Revenues | B31: 945816 | C31: 1469521 | D31: 2372300 | E31: =E33*E32 -> 3192485.3 | F31: =F33*F32 -> 4633674.1 | G31: =G33*G32 -> 6493777.2 | H31: =H33*H32 -> 8451206.7 | I31: 2018 | J31: 2019 | K31: 2020
A32: Average yearly revenue per membership | B32: =I32*12 -> 133.92 | C32: =J32*12 -> 150.84 | D32: =K32*12 -> 159.84 | E32: =AVERAGE($B$32:$D$32) -> 148.2 | F32: =AVERAGE($B$32:$D$32) -> 148.2 | G32: =AVERAGE($B$32:$D$32) -> 148.2 | H32: =AVERAGE($B$32:$D$32) -> 148.2 | I32: 11.16 | J32: 12.57 | K32: 13.32
A33: Average paid membership | B33: =B31/B32 -> 7062.5448 | C33: =C31/C32 -> 9742.2501 | D33: =D31/D32 -> 14841.717 | E33: =D33*(1+E34) -> 21541.736 | F33: =E33*(1+F34) -> 31266.357 | G33: =F33*(1+G34) -> 43817.66 | H33: =G33*(1+H34) -> 57025.686
A34: Growth % | C34: =C33/B33-1 -> 0.37942489 | D34: =D33/C33-1 -> 0.52343828 | E34: =AVERAGE($C$34:$D$34) -> 0.45143159 | F34: =AVERAGE($C$34:$D$34) -> 0.45143159 | G34: =F34-5% -> 0.40143159 | H34: =G34-10% -> 0.30143159

Sheet Other items
A1: Other items
A3: in thousands | B3: 2018 | C3: 2019 | D3: 2020 | E3: 2021 Forcasted | F3: 2022 Forcasted | G3: 2023 Forcasted | H3: 2024 Forcasted
A4: Cost of goods sold | B4: ='P&L'!B5 -> 9967538 | C4: ='P&L'!C5 -> 12440213 | D4: ='P&L'!D5 -> 15276319 | E4: ='Revenue Modelling'!E3*'Other items'!E5 -> 17476551 | F4: ='Revenue Modelling'!F3*'Other items'!F5 -> 20507738 | G4: ='Revenue Modelling'!G3*'Other items'!G5 -> 23362117 | H4: ='Revenue Modelling'!H3*'Other items'!H5 -> 26217152
A5: as a % revenues | B5: =B4/'Revenue Modelling'!B6 -> 0.61680577 | C5: =C4/'Revenue Modelling'!C6 -> 0.6082144 | D5: =D4/'Revenue Modelling'!D6 -> 0.60535667 | E5: =AVERAGE(($B$5:$D$5)) -> 0.61012561 | F5: =AVERAGE(($B$5:$D$5)) -> 0.61012561 | G5: =AVERAGE(($B$5:$D$5)) -> 0.61012561 | H5: =AVERAGE(($B$5:$D$5)) -> 0.61012561
A7: Marketing | B7: ='P&L'!B6 -> 2369469 | C7: ='P&L'!C6 -> 2652462 | D7: ='P&L'!D6 -> 2228362 | E7: ='Revenue Modelling'!E6*'Other items'!E8 -> 3504858.9 | F7: ='Revenue Modelling'!F6*'Other items'!F8 -> 4104178.5 | G7: ='Revenue Modelling'!G6*'Other items'!G8 -> 4669136.1 | H7: ='Revenue Modelling'!H6*'Other items'!H8 -> 5234918.4
A8: as a % revenues | B8: =B7/'Revenue Modelling'!B6 -> 0.14662619 | C8: =C7/'Revenue Modelling'!C6 -> 0.12968151 | D8: =D7/'Revenue Modelling'!D6 -> 0.088303589 | E8: =AVERAGE($B$8:$D$8) -> 0.1215371 | F8: =AVERAGE($B$8:$D$8) -> 0.1215371 | G8: =AVERAGE($B$8:$D$8) -> 0.1215371 | H8: =AVERAGE($B$8:$D$8) -> 0.1215371
A10: Technology and development | B10: 1221814 | C10: 1545149 | D10: 1829600 | E10: ='Revenue Modelling'!E6*'Other items'!E11 -> 2149887.5 | F10: ='Revenue Modelling'!F6*'Other items'!F11 -> 2517511.4 | G10: ='Revenue Modelling'!G6*'Other items'!G11 -> 2864057.5 | H10: ='Revenue Modelling'!H6*'Other items'!H11 -> 3211109.5
A11: as a % revenues | B11: =B10/'Revenue Modelling'!B6 -> 0.075607629 | C11: =C10/'Revenue Modelling'!C6 -> 0.075543873 | D11: =D10/'Revenue Modelling'!D6 -> 0.072501796 | E11: =AVERAGE($B$11:$D$11) -> 0.0745511 | F11: =AVERAGE($B$11:$D$11) -> 0.0745511 | G11: =AVERAGE($B$11:$D$11) -> 0.0745511 | H11: =AVERAGE($B$11:$D$11) -> 0.0745511
A13: General and administrative | B13: 630294 | C13: 914369 | D13: 1076486 | E13: ='Revenue Modelling'!E6*'Other items'!E14 -> 1214704.3 | F13: ='Revenue Modelling'!F6*'Other items'!F14 -> 1422414.8 | G13: ='Revenue Modelling'!G6*'Other items'!G14 -> 1618216.3 | H13: ='Revenue Modelling'!H6*'Other items'!H14 -> 1814303.5
A14: as a % revenues | B14: =B13/'Revenue Modelling'!B6 -> 0.039003511 | C14: =C13/'Revenue Modelling'!C6 -> 0.044704411 | D14: =D13/'Revenue Modelling'!D6 -> 0.04265805 | E14: =AVERAGE($B$14:$D$14) -> 0.04212199 | F14: =AVERAGE($B$14:$D$14) -> 0.04212199 | G14: =AVERAGE($B$14:$D$14) -> 0.04212199 | H14: =AVERAGE($B$14:$D$14) -> 0.04212199
A16: Other current asssets | B16: 5899652 | C16: 1160067 | D16: 1556030 | E16: ='Revenue Modelling'!E6*'Other items'!E17 -> 1778165.8 | F16: ='Revenue Modelling'!F6*'Other items'!F17 -> 2082226.5 | G16: ='Revenue Modelling'!G6*'Other items'!G17 -> 2368853.8 | H16: ='Revenue Modelling'!H6*'Other items'!H17 -> 2655899.5
A17: as a % revenues | B17: =B16/'Revenue Modelling'!B6 -> 0.36507906 | C17: =C16/'Revenue Modelling'!C6 -> 0.056716831 | D17: =D16/'Revenue Modelling'!D6 -> 0.061661002 | E17: =$D$17 -> 0.061661002 | F17: =$D$17 -> 0.061661002 | G17: =$D$17 -> 0.061661002 | H17: =$D$17 -> 0.061661002
A19: Accounts payable | B19: 562985 | C19: 674347 | D19: 656183 | E19: =(E20*E4)/365 -> 750692.36 | F19: =(F20*F4)/365 -> 880894.75 | G19: =(G20*G4)/365 -> 1003502.5 | H19: =(H20*H4)/365 -> 1126138.4
A20: Days Payable | B20: =B19/B4*365 -> 20.615876 | C20: =C19/C4*365 -> 19.785566 | D20: =D19/D4*365 -> 15.678305 | E20: =$D$20 -> 15.678305 | F20: =$D$20 -> 15.678305 | G20: =$D$20 -> 15.678305 | H20: =$D$20 -> 15.678305
A22: Accured expenses and other liabilities | B22: 481874 | C22: 843043 | D22: 1102196 | E22: ='Revenue Modelling'!E6*'Other items'!E23 -> 1102690.4 | F22: ='Revenue Modelling'!F6*'Other items'!F23 -> 1291246.9 | G22: ='Revenue Modelling'!G6*'Other items'!G23 -> 1468992.5 | H22: ='Revenue Modelling'!H6*'Other items'!H23 -> 1646997.6
A23: as a % revenues | B23: =B22/'Revenue Modelling'!B6 -> 0.029819065 | C23: =C22/'Revenue Modelling'!C6 -> 0.041217212 | D23: =$D$22/'Revenue Modelling'!D6 -> 0.043676863 | E23: =AVERAGE($B$23:$D$23) -> 0.038237713 | F23: =AVERAGE($B$23:$D$23) -> 0.038237713 | G23: =AVERAGE($B$23:$D$23) -> 0.038237713 | H23: =AVERAGE($B$23:$D$23) -> 0.038237713
A25: Deffered revenue | B25: 760899 | C25: 924745 | D25: 1117992 | E25: ='Revenue Modelling'!E6*'Other items'!E26 -> 1313080.4 | F25: ='Revenue Modelling'!F6*'Other items'!F26 -> 1537612.9 | G25: ='Revenue Modelling'!G6*'Other items'!G26 -> 1749271.8 | H25: ='Revenue Modelling'!H6*'Other items'!H26 -> 1961239.7
A26: as a % revenues | B26: =B25/'Revenue Modelling'!B6 -> 0.047085538 | C26: =C25/'Revenue Modelling'!C6 -> 0.045211704 | D26: =D25/'Revenue Modelling'!D6 -> 0.044302814 | E26: =AVERAGE($B$26:$D$26) -> 0.045533352 | F26: =AVERAGE($B$26:$D$26) -> 0.045533352 | G26: =AVERAGE($B$26:$D$26) -> 0.045533352 | H26: =AVERAGE($B$26:$D$26) -> 0.045533352

Sheet Schedules
A1: PP & E
A3: in thousands | B3: 2018 | C3: 2019 | D3: 2020 | E3: 2021 Forcasted | F3: 2022 Forcasted | G3: 2023 Forcasted | H3: 2024 Forcasted
A4: Beginning Balance | C4: =B7 -> 418281 | D4: =C7 -> 565221 | E4: =D7 -> 960183 | F4: =E7 -> 1284140.1 | G4: =F7 -> 1580571.3 | H4: =G7 -> 1855677.9
A5: add: Capex | C5: =C7+C6-C4 -> 250519 | D5: =$D$7+$D$6-$D$4 -> 510672 | E5: =$D$7+$D$6-$D$4 -> 510672 | F5: =$D$7+$D$6-$D$4 -> 510672 | G5: =$D$7+$D$6-$D$4 -> 510672 | H5: =$D$7+$D$6-$D$4 -> 510672
A6: less: Depreciation | B6: 83157 | C6: 103579 | D6: 115710 | E6: =(E4+E5)/E9 -> 186714.87 | F6: =(F4+F5)/F9 -> 214240.79 | G6: =(G4+G5)/G9 -> 235565.47 | H6: =(H4+H5)/H9 -> 252342.12
A7: Closing Balance | B7: ='Balance Sheet'!B10 -> 418281 | C7: ='Balance Sheet'!C10 -> 565221 | D7: ='Balance Sheet'!D10 -> 960183 | E7: =E4+E5-E6 -> 1284140.1 | F7: =F4+F5-F6 -> 1580571.3 | G7: =G4+G5-G6 -> 1855677.9 | H7: =H4+H5-H6 -> 2114007.8
A9: Useful life | C9: =(C4+C5)/C6 -> 6.4569073 | D9: =(D4+D5)/D6 -> 9.2981851 | E9: =AVERAGE(C9:D9) -> 7.8775462 | F9: =E9+0.5 -> 8.3775462 | G9: =F9+0.5 -> 8.8775462 | H9: =G9+0.5 -> 9.3775462
A12: Content Assets
A13: in thousands | B13: 2018 | C13: 2019 | D13: 2020 | E13: 2021 Forcasted | F13: 2022 Forcasted | G13: 2023 Forcasted | H13: 2024 Forcasted
A14: Beginning Balance | C14: =B17 -> 14951141 | D14: =C17 -> 24504567 | E14: =D17 -> 25383950 | F14: =E17 -> 26490395 | G14: =F17 -> 27281060 | H14: =G17 -> 27846069
A15: add: Adition to Content Assets | C15: =C17+C16-C14 -> 18769673 | D15: =$D$17+$D$16-$D$14 -> 11686295 | E15: =$D$17+$D$16-$D$14 -> 11686295 | F15: =$D$17+$D$16-$D$14 -> 11686295 | G15: =$D$17+$D$16-$D$14 -> 11686295 | H15: =$D$17+$D$16-$D$14 -> 11686295
A16: less: Amortisation of Content Assets | C16: 9216247 | D16: 10806912 | E16: =(E14+E15)/E19 -> 10579850 | F16: =(F14+F15)/F19 -> 10895630 | G16: =(G14+G15)/G19 -> 11121286 | H16: =(H14+H15)/H19 -> 11282539
A17: Closing Balance | B17: ='Balance Sheet'!B9 -> 14951141 | C17: ='Balance Sheet'!C9 -> 24504567 | D17: ='Balance Sheet'!D9 -> 25383950 | E17: =E14+E15-E16 -> 26490395 | F17: =F14+F15-F16 -> 27281060 | G17: =G14+G15-G16 -> 27846069 | H17: =H14+H15-H16 -> 28249825
A19: Useful life | C19: =(C14+C15)/C16 -> 3.6588444 | D19: =(D14+D15)/D16 -> 3.3488625 | E19: =AVERAGE($C$19:$D$19) -> 3.5038534 | F19: =AVERAGE($C$19:$D$19) -> 3.5038534 | G19: =AVERAGE($C$19:$D$19) -> 3.5038534 | H19: =AVERAGE($C$19:$D$19) -> 3.5038534
A22: Debt Schedule
A23: Beginning Balance of Debt | C23: =B25 -> 10360058 | D23: =C25 -> 14759260 | E23: =D25 -> 15809095 | F23: =E25 -> 15309095 | G23: =F25 -> 14609095 | H23: =G25 -> 14609095
A24: add/less: Debt Taken/(debt repaid) | C24: =C25-C23 -> 4399202 | D24: =D25-D23 -> 1049835 | E24: -500000 | F24: -700000 | G24: 0 | H24: -400000
A25: Closing Balance | B25: ='Balance Sheet'!B23 -> 10360058 | C25: ='Balance Sheet'!C23 -> 14759260 | D25: ='Balance Sheet'!D23 -> 15809095 | E25: =E23+E24 -> 15309095 | F25: =F23+F24 -> 14609095 | G25: =G23+G24 -> 14609095 | H25: =H23+H24 -> 14209095
A27: Interest Expense | B27: ='P&L'!B11 -> -420493 | C27: ='P&L'!C11 -> -626023 | D27: ='P&L'!D11 -> -767499 | E27: =E25*E28 -> -696284.81 | F27: =F25*F28 -> -664447.57 | G27: =G25*G28 -> -664447.57 | H27: =H25*H28 -> -646254.86
B28: =B27/B25 -> -0.0405879 | C28: =C27/C25 -> -0.042415609 | D28: =D27/D25 -> -0.04854794 | E28: =AVERAGE($C$28:$D$28) -> -0.045481775 | F28: =AVERAGE($C$28:$D$28) -> -0.045481775 | G28: =AVERAGE($C$28:$D$28) -> -0.045481775 | H28: =AVERAGE($C$28:$D$28) -> -0.045481775

Sheet P&L Forcasting
A1: P & L Forcasting
A3: in thousands | B3: 2018 | C3: 2019 | D3: 2020 | E3: 2021 Forcasted | F3: 2022 Forcasted | G3: 2023 Forcasted | H3: 2024 Forcasted
A4: Streaming revenues | B4: ='Revenue Modelling'!B3 -> 15794341 | C4: ='Revenue Modelling'!C3 -> 20156447 | D4: ='Revenue Modelling'!D3 -> 24995956 | E4: ='Revenue Modelling'!E3 -> 28644186 | F4: ='Revenue Modelling'!F3 -> 33612322 | G4: ='Revenue Modelling'!G3 -> 38290668 | H4: ='Revenue Modelling'!H3 -> 42970088
A5: DVD Revenues | B5: ='Revenue Modelling'!B4 -> 365589 | C5: ='Revenue Modelling'!C4 -> 297217 | D5: ='Revenue Modelling'!D4 -> 239281 | E5: ='Revenue Modelling'!E4 -> 193584.67 | F5: ='Revenue Modelling'!F4 -> 156615.12 | G5: ='Revenue Modelling'!G4 -> 126705.78 | H5: ='Revenue Modelling'!H4 -> 102508.33
A6: Total Revenues | B6: ='Revenue Modelling'!B6 -> 16159930 | C6: ='Revenue Modelling'!C6 -> 20453664 | D6: ='Revenue Modelling'!D6 -> 25235237 | E6: ='Revenue Modelling'!E6 -> 28837771 | F6: ='Revenue Modelling'!F6 -> 33768937 | G6: ='Revenue Modelling'!G6 -> 38417374 | H6: ='Revenue Modelling'!H6 -> 43072597
A7: Cost of Goods sold | B7: ='Other items'!B4 -> 9967538 | C7: ='Other items'!C4 -> 12440213 | D7: ='Other items'!D4 -> 15276319 | E7: ='Other items'!E4 -> 17476551 | F7: ='Other items'!F4 -> 20507738 | G7: ='Other items'!G4 -> 23362117 | H7: ='Other items'!H4 -> 26217152
A8: Gross Margin | B8: =B6-B7 -> 6192392 | C8: =C6-C7 -> 8013451 | D8: =D6-D7 -> 9958918 | E8: =E6-E7 -> 11361219 | F8: =F6-F7 -> 13261198 | G8: =G6-G7 -> 15055257 | H8: =H6-H7 -> 16855445
A9: Operating Expenses
A10: Marketing | B10: ='Other items'!B7 -> 2369469 | C10: ='Other items'!C7 -> 2652462 | D10: ='Other items'!D7 -> 2228362 | E10: ='Other items'!E7 -> 3504858.9 | F10: ='Other items'!F7 -> 4104178.5 | G10: ='Other items'!G7 -> 4669136.1 | H10: ='Other items'!H7 -> 5234918.4
A11: Technology and development | B11: ='Other items'!B10 -> 1221814 | C11: ='Other items'!C10 -> 1545149 | D11: ='Other items'!D10 -> 1829600 | E11: ='Other items'!E10 -> 2149887.5 | F11: ='Other items'!F10 -> 2517511.4 | G11: ='Other items'!G10 -> 2864057.5 | H11: ='Other items'!H10 -> 3211109.5
A12: General and administrative | B12: ='Other items'!B13 -> 630294 | C12: ='Other items'!C13 -> 914369 | D12: ='Other items'!D13 -> 1076486 | E12: ='Other items'!E13 -> 1214704.3 | F12: ='Other items'!F13 -> 1422414.8 | G12: ='Other items'!G13 -> 1618216.3 | H12: ='Other items'!H13 -> 1814303.5
A13: EBITDA | B13: =B8-SUM(B10:B12) -> 1970815 | C13: =C8-SUM(C10:C12) -> 2901471 | D13: =D8-SUM(D10:D12) -> 4824470 | E13: =E8-SUM(E10:E12) -> 4491768.4 | F13: =F8-SUM(F10:F12) -> 5217093.7 | G13: =G8-SUM(G10:G12) -> 5903846.8 | H13: =H8-SUM(H10:H12) -> 6595114
A14: less: Depreciation | B14: =Schedules!B6 -> 83157 | C14: =Schedules!C6 -> 103579 | D14: =Schedules!D6 -> 115710 | E14: =Schedules!E6 -> 186714.87 | F14: =Schedules!F6 -> 214240.79 | G14: =Schedules!G6 -> 235565.47 | H14: =Schedules!H6 -> 252342.12
A15: EBIT | B15: =B13-B14 -> 1887658 | C15: =C13-C14 -> 2797892 | D15: =D13-D14 -> 4708760 | E15: =E13-E14 -> 4305053.5 | F15: =F13-F14 -> 5002853 | G15: =G13-G14 -> 5668281.3 | H15: =H13-H14 -> 6342771.8
A16: Interest | B16: =Schedules!B27 -> -420493 | C16: =Schedules!C27 -> -626023 | D16: =Schedules!D27 -> -767499 | E16: =Schedules!E27 -> -696284.81 | F16: =Schedules!F27 -> -664447.57 | G16: =Schedules!G27 -> -664447.57 | H16: =Schedules!H27 -> -646254.86
A17: Interest and other income( expense) | B17: ='P&L'!B12 -> 41725 | C17: ='P&L'!C12 -> 84000 | D17: ='P&L'!D12 -> -618441 | E17: 0 | F17: 0 | G17: 0 | H17: 0
A18: EBT | B18: =B15+B16+B17 -> 1508890 | C18: =C15+C16+C17 -> 2255869 | D18: =D15+D16+D17 -> 3322820 | E18: =E15+E16+E17 -> 3608768.7 | F18: =F15+F16+F17 -> 4338405.4 | G18: =G15+G16+G17 -> 5003833.8 | H18: =H15+H16+H17 -> 5696517
A19: Taxes | B19: ='P&L'!B14 -> -15216 | C19: ='P&L'!C14 -> -195315 | D19: ='P&L'!D14 -> -437954 | E19: =E18*E20 -> -547850.3 | F19: =F18*F20 -> -658617.07 | G19: =G18*G20 -> -759636.33 | H19: =H18*H20 -> -864793.17
A20: tax rate% | B20: =B19/B21 -> -0.010186962 | C20: =C19/C21 -> -0.094787615 | D20: =$D$19/$D$21 -> -0.15181086 | E20: =$D$19/$D$21 -> -0.15181086 | F20: =$D$19/$D$21 -> -0.15181086 | G20: =$D$19/$D$21 -> -0.15181086 | H20: =$D$19/$D$21 -> -0.15181086
A21: Net Income | B21: =B18+B19 -> 1493674 | C21: =C18+C19 -> 2060554 | D21: =D18+D19 -> 2884866 | E21: =E18+E19 -> 3060918.4 | F21: =F18+F19 -> 3679788.3 | G21: =G18+G19 -> 4244197.4 | H21: =H18+H19 -> 4831723.8

Sheet Balance Sheet 
A1: Balance Sheet
A3: in thousands | B3: 2018 | C3: 2019 | D3: 2020 | E3: 2021 Forcasted | F3: 2022 Forcasted | G3: 2023 Forcasted | H3: 2024 Forcasted
A4: Assets
A5: Current assets
A6: Cash and cash equivalents | B6: 3794483 | C6: 5018437 | D6: 8205550 | E6: 8205550 | F6: 8205550 | G6: 8205550 | H6: 8205550
A7: Other current asssets | B7: 5899652 | C7: 1160067 | D7: 1556030 | E7: 1556030 | F7: 1556030 | G7: 1556030 | H7: 1556030
A8: Total current assets | B8: =SUM(B6:B7) -> 9694135 | C8: =SUM(C6:C7) -> 6178504 | D8: =SUM(D6:D7) -> 9761580 | E8: =SUM(E6:E7) -> 9761580 | F8: =SUM(F6:F7) -> 9761580 | G8: =SUM(G6:G7) -> 9761580 | H8: =SUM(H6:H7) -> 9761580
A9: content assets, net | B9: 14951141 | C9: 24504567 | D9: 25383950 | E9: 25383950 | F9: 25383950 | G9: 25383950 | H9: 25383950
A10: property and equipment, net | B10: 418281 | C10: 565221 | D10: 960183 | E10: 960183 | F10: 960183 | G10: 960183 | H10: 960183
A11: Other non-current assets | B11: 910843 | C11: 2727420 | D11: 3174646 | E11: 3174646 | F11: 3174646 | G11: 3174646 | H11: 3174646
A12: Total assets | B12: =SUM(B8:B11) -> 25974400 | C12: =SUM(C8:C11) -> 33975712 | D12: =SUM(D8:D11) -> 39280359 | E12: =SUM(E8:E11) -> 39280359 | F12: =SUM(F8:F11) -> 39280359 | G12: =SUM(G8:G11) -> 39280359 | H12: =SUM(H8:H11) -> 39280359
A14: Liabilities and Stockholders equity
A15: Current liabilities
A16: Current content liabilities | B16: 4681562 | C16: 4413561 | D16: 4429536 | E16: 4429536 | F16: 4429536 | G16: 4429536 | H16: 4429536
A17: Accounts payable | B17: 562985 | C17: 674347 | D17: 656183 | E17: 656183 | F17: 656183 | G17: 656183 | H17: 656183
A18: Accured expenses and other liabilities | B18: 481874 | C18: 843043 | D18: 1102196 | E18: 1102196 | F18: 1102196 | G18: 1102196 | H18: 1102196
A19: Deffered revenue | B19: 760899 | C19: 924745 | D19: 1117992 | E19: 1117992 | F19: 1117992 | G19: 1117992 | H19: 1117992
A20: Short term debt | D20: 499878 | E20: 499878 | F20: 499878 | G20: 499878 | H20: 499878
A21: Total current liabilities | B21: =SUM(B16:B20) -> 6487320 | C21: =SUM(C16:C20) -> 6855696 | D21: =SUM(D16:D20) -> 7805785 | E21: =SUM(E16:E20) -> 7805785 | F21: =SUM(F16:F20) -> 7805785 | G21: =SUM(G16:G20) -> 7805785 | H21: =SUM(H16:H20) -> 7805785
A22: Non-current content liabilities | B22: 3759026 | C22: 3334323 | D22: 2618084 | E22: 2618084 | F22: 2618084 | G22: 2618084 | H22: 2618084
A23: Long-term debt | B23: 10360058 | C23: 14759260 | D23: 15809095 | E23: 15809095 | F23: 15809095 | G23: 15809095 | H23: 15809095
A24: Other non-current liabilities | B24: 129231 | C24: 1444276 | D24: 1982155 | E24: 1982155 | F24: 1982155 | G24: 1982155 | H24: 1982155
A25: Total liabilities | B25: =SUM(B21:B24) -> 20735635 | C25: =SUM(C21:C24) -> 26393555 | D25: =SUM(D21:D24) -> 28215119 | E25: =SUM(E21:E24) -> 28215119 | F25: =SUM(F21:F24) -> 28215119 | G25: =SUM(G21:G24) -> 28215119 | H25: =SUM(H21:H24) -> 28215119
A26: Stockholders equity
A27: Common Stock | B27: 2315988 | C27: 2793929 | D27: 3447698 | E27: 3447698 | F27: 3447698 | G27: 3447698 | H27: 3447698
A28: Treasury stock
A29: Accumulated other comprehensive income (loss) | B29: -19582 | C29: -23521 | D29: 44398 | E29: 44398 | F29: 44398 | G29: 44398 | H29: 44398
A30: Retained earnings | B30: 2942359 | C30: 4811749 | D30: 7573144 | E30: 7573144 | F30: 7573144 | G30: 7573144 | H30: 7573144
A31: Total stockholders equity | B31: =SUM(B27:B30) -> 5238765 | C31: =SUM(C27:C30) -> 7582157 | D31: =SUM(D27:D30) -> 11065240 | E31: =SUM(E27:E30) -> 11065240 | F31: =SUM(F27:F30) -> 11065240 | G31: =SUM(G27:G30) -> 11065240 | H31: =SUM(H27:H30) -> 11065240
A32: Total liabilities and stockholders equity | B32: =SUM(B25+B31) -> 25974400 | C32: =SUM(C25+C31) -> 33975712 | D32: =SUM(D25+D31) -> 39280359 | E32: =SUM(E25+E31) -> 39280359 | F32: =SUM(F25+F31) -> 39280359 | G32: =SUM(G25+G31) -> 39280359 | H32: =SUM(H25+H31) -> 39280359
A35: Check | B35: =B32=B12 -> TRUE | C35: =C32=C12 -> TRUE | D35: =D32=D12 -> TRUE | E35: =E32=E12 -> TRUE | F35: =F32=F12 -> TRUE | G35: =G32=G12 -> TRUE | H35: =H32=H12 -> TRUE

Sheet Cash flow statement
A1: Cash Flow
A3: in thousands | B3: 2018 | C3: 2019 | D3: 2020 | E3: 2021 Forcasted | F3: 2022 Forcasted | G3: 2023 Forcasted | H3: 2024 Forcasted
A4: EBIT | E4: ='P&L Forcasting'!E15 -> 4305053.5 | F4: ='P&L Forcasting'!F15 -> 5002853 | G4: ='P&L Forcasting'!G15 -> 5668281.3 | H4: ='P&L Forcasting'!H15 -> 6342771.8
A5: Operating Taxes | E5: =E4*E6 -> -653553.9 | F5: =F4*F6 -> -759487.43 | G5: =G4*G6 -> -860506.69 | H5: =H4*H6 -> -962901.67
A6: Op tax rate % | E6: ='P&L Forcasting'!E20 -> -0.15181086 | F6: ='P&L Forcasting'!F20 -> -0.15181086 | G6: ='P&L Forcasting'!G20 -> -0.15181086 | H6: ='P&L Forcasting'!H20 -> -0.15181086
A7: NOPAT | E7: =E4+E5 -> 3651499.6 | F7: =F4+F5 -> 4243365.5 | G7: =G4+G5 -> 4807774.6 | H7: =H4+H5 -> 5379870.2
A8: add Amortization | E8: =Schedules!E16 -> 10579850 | F8: =Schedules!F16 -> 10895630 | G8: =Schedules!G16 -> 11121286 | H8: =Schedules!H16 -> 11282539
A9: add Depreciation | E9: =Schedules!E6 -> 186714.87 | F9: =Schedules!F6 -> 214240.79 | G9: =Schedules!G6 -> 235565.47 | H9: =Schedules!H6 -> 252342.12
A10: Gross Cash flow | E10: =E7+E8+E9 -> 14418065 | F10: =F7+F8+F9 -> 15353236 | G10: =G7+G8+G9 -> 16164626 | H10: =H7+H8+H9 -> 16914752
A11: Accounts Payables | E11: ='Other items'!E19-'Other items'!D19 -> 94509.359 | F11: ='Other items'!F19-'Other items'!E19 -> 130202.4 | G11: ='Other items'!G19-'Other items'!F19 -> 122607.74 | H11: ='Other items'!H19-'Other items'!G19 -> 122635.88
A12: Deffered Revenue | E12: ='Other items'!E25-'Other items'!D25 -> 195088.35 | F12: ='Other items'!F25-'Other items'!E25 -> 224532.53 | G12: ='Other items'!G25-'Other items'!F25 -> 211658.92 | H12: ='Other items'!H25-'Other items'!G25 -> 211967.9
A13: Current content liabilities
A14: Accured expenses & other liabilities
A15: Other current assets | E15: ='Other items'!E16-'Other items'!D16 -> 222135.83 | F15: ='Other items'!F16-'Other items'!E16 -> 304060.66 | G15: ='Other items'!G16-'Other items'!F16 -> 286627.29 | H15: ='Other items'!H16-'Other items'!G16 -> 287045.7
A16: Investment in working Capital | E16: =E10-SUM(E11:E15) -> 13906331
A17: Content Assets | E17: =Schedules!E15 -> 11686295 | F17: =Schedules!F15 -> 11686295 | G17: =Schedules!G15 -> 11686295 | H17: =Schedules!H15 -> 11686295
A18: PP &E
A19: Capex | E19: =-SUM(E17:E18) -> -11686295 | F19: =-SUM(F17:F18) -> -11686295 | G19: =-SUM(G17:G18) -> -11686295 | H19: =-SUM(H17:H18) -> -11686295
A20: Extraodinary items | E20: =Schedules!E5 -> 510672 | F20: =Schedules!F5 -> 510672 | G20: =Schedules!G5 -> 510672 | H20: =Schedules!H5 -> 510672
A21: UFCF | E21: =SUM(E10:E20) -> 29346802 | F21: =SUM(F10:F20) -> 16522704 | G21: =SUM(G10:G20) -> 17296192 | H21: =SUM(H10:H20) -> 18047073
A22: Debt taken (Repaid) | E22: =Schedules!E24 -> -500000 | F22: =Schedules!F24 -> -700000 | G22: =Schedules!G24 -> 0 | H22: =Schedules!H24 -> -400000
A23: Interest Expenses | E23: =Schedules!E27 -> -696284.81 | F23: =Schedules!F27 -> -664447.57 | G23: =Schedules!G27 -> -664447.57 | H23: =Schedules!H27 -> -646254.86
A24: diff bw actual and Op taxes | E24: ='P&L Forcasting'!E19-'Cash flow statement'!E5 -> 105703.6 | F24: ='P&L Forcasting'!F19-'Cash flow statement'!F5 -> 100870.36 | G24: ='P&L Forcasting'!G19-'Cash flow statement'!G5 -> 100870.36 | H24: ='P&L Forcasting'!H19-'Cash flow statement'!H5 -> 98108.508
A25: Net Cash flow | E25: =SUM(E21:E24) -> 28256220 | F25: =SUM(F21:F24) -> 15259126 | G25: =SUM(G21:G24) -> 16732614 | H25: =SUM(H21:H24) -> 17098927

Sheet WACC
A1: WACC
A3: Risk free Rate | B3: 1.67
A4: Market Risk Premium | B4: 0.055
A5: Beta | B5: 0.01058
A7: in thousands | B7: Amount
A9: Cost of Equity | B9: =B3*B5+B4 -> 0.0726686
A10: Cost Debt | B10: 0.0488
A12: Equity | B12: ='Balance Sheet '!H31 -> 11065240
A13: Debt | B13: ='Balance Sheet '!H23 -> 15809095
A15: Equity/(Equity+Debt) | B15: =B12/(B12+B13) -> 0.41174005
A16: Debt/(Equity+Debt) | B16: =B13/(B12+B13) -> 0.58825995
A18: WACC | B18: =B9*B15+B10*B16 -> 0.058627659

Sheet DCF
A1: DCF Analysis
A4: in thousands | B4: 2021 Forcasted | C4: 2022 Forcasted | D4: 2023 Forcasted | E4: 2024 Forcasted
A5: UFCF | B5: ='Cash flow statement'!E21 -> 29346802 | C5: ='Cash flow statement'!F21 -> 16522704 | D5: ='Cash flow statement'!G21 -> 17296192 | E5: ='Cash flow statement'!H21 -> 18047073
A6: Discounting Factor | B6: =1/(1+WACC!$B$18)^DCF!B7 -> 0.94461919 | C6: =1/(1+WACC!$B$18)^DCF!C7 -> 0.89230541 | D6: =1/(1+WACC!$B$18)^DCF!D7 -> 0.84288881 | E6: =1/(1+WACC!$B$18)^DCF!E7 -> 0.79620895
A7: No of years | B7: 1 | C7: 2 | D7: 3 | E7: 4
A9: PV OF UFCF | B9: =B5*B6 -> 27721552 | C9: =C5*C6 -> 14743298 | D9: =D5*D6 -> 14578767 | E9: =E5*E6 -> 14369241
A11: Sum of PV | B11: =SUM(B9:E9) -> 71412857
A13: Terminal Value | B13: =E5*(1+WACC!B3)/(WACC!B18-WACC!B3) -> -29903508
A15: pv of terminal value | B15: =B13*E6 -> -23809440
A18: Enterprise Value | B18: =B11+B15 -> 47603417
A20: Debt | B20: ='Balance Sheet '!H23 -> 15809095
A22: Equity | B22: ='Balance Sheet '!H6 -> 8205550
A24: Equity Value | B24: =B22+B18-B20 -> 39999872
